LICENSE
README.md
setup.py
jaal/__init__.py
jaal/jaal.py
jaal/layout.py
jaal/assest/logo.png
jaal/datasets/__init__.py
jaal/datasets/load_got.py
jaal/datasets/parse_dataframe.py
jaal/datasets/got/got_edge_df.csv
jaal/datasets/got/got_node_df.csv
ncnetworkviz.egg-info/PKG-INFO
ncnetworkviz.egg-info/SOURCES.txt
ncnetworkviz.egg-info/dependency_links.txt
ncnetworkviz.egg-info/requires.txt
ncnetworkviz.egg-info/top_level.txt