Metadata-Version: 2.1
Name: ncnetworkviz
Version: 0.1.1
Summary: small update of jaal
Home-page: https://github.com/Qotov/jaal
Author: Mohit Mayank / (modified by A. Kotov)
Author-email: alexander.o.kotov@gmail.com
License: UNKNOWN
Platform: UNKNOWN
Classifier: Programming Language :: Python :: 3
Classifier: License :: OSI Approved :: MIT License
Classifier: Operating System :: OS Independent
Requires-Python: >=3.6
License-File: LICENSE
